dataclasses_json-stubs/__init__.pyi
dataclasses_json-stubs/api.pyi
dataclasses_json-stubs/cfg.pyi
dataclasses_json-stubs/core.pyi
dataclasses_json-stubs/mm.pyi
dataclasses_json-stubs/stringcase.pyi
dataclasses_json-stubs/undefined.pyi
dataclasses_json-stubs/utils.pyi
types_dataclasses_json-0.5.9.dist-info/LICENSE
types_dataclasses_json-0.5.9.dist-info/METADATA
types_dataclasses_json-0.5.9.dist-info/WHEEL
types_dataclasses_json-0.5.9.dist-info/RECORD
